cloudtoken_plugin/__init__.py
cloudtoken_plugin/adfs.py
cloudtoken_plugin.adfs-0.1.764.dist-info/LICENSE.txt
cloudtoken_plugin.adfs-0.1.764.dist-info/METADATA
cloudtoken_plugin.adfs-0.1.764.dist-info/WHEEL
cloudtoken_plugin.adfs-0.1.764.dist-info/top_level.txt
cloudtoken_plugin.adfs-0.1.764.dist-info/RECORD
